Lab5_20160521_LeeJunhee/DFF_SR.v
// DFF_SR module
module DFF_SR(
		input wire R, S, D, CLK,
		output reg Q, QN,
		output wire val);

///////////////////////////////////////////////
////////// Write your own code here! //////////
assign val = Q ^ QN;

always @ ( posedge CLK ) begin
	if ({R, S} == 2'b0_0) begin
		{Q, QN} = {D, ~D};
	end
	else if ({R, S} == 2'b1_0) begin
		{Q, QN} = 2'b0_1;
	end
	else if ({R, S} == 2'b0_1) begin
		{Q, QN} = 2'b1_0;
	end
	else if ({R, S} == 2'b1_1) begin
		{Q, QN} = 2'b1_1;
	end
	else begin
		{Q, QN} = 2'b0_0;
	end
end
///////////////////////////////////////////////

endmodule

Lab5_20160521_LeeJunhee/tb_DFF_SR.v
// Testing workbench module for Synchronous Set-Reset D-Flip Flop
`timescale 1ns/1ps	// Simulation precision

module TEST_BENCH_DFF_SR;

///////////////////////////////////////////////
////////// Write your own code here! //////////
	parameter CLK_FREQ = 100;
	reg rst;
	reg CLK;

	reg  [3:0] sol_cnt;
	reg R, S ,D;
	wire Q, QN, val;

	///////////////////////////////////////

	initial begin
	  CLK = 0;
	  #1;
	  forever begin
	    CLK = #((1000/CLK_FREQ)/2) ~CLK;
	  end
	end

	///////////////////////////////////////

	DFF_SR u_DFFSR(R, S, D, CLK, Q, QN, val);

	initial begin

	sol_cnt = 0;
	{R, S, D} = 3'b0_0_0;
	#10
	$display("R = %b, S = %b, D = %b, Q = %b, Q' = %b, val = %b", R, S, D, Q, QN, val);
	#10
	if ({Q, QN, val} == 3'b0_1_1) begin
		$display ("Case 1 is passed");
		sol_cnt = sol_cnt + 1;
	end
	else begin
		$display ("Case 1 is failed");
	end

	{R, S, D} = 3'b0_0_1;
	#10
	$display("R = %b, S = %b, D = %b, Q = %b, Q' = %b, val = %b", R, S, D, Q, QN, val);
	#10
	if ({Q, QN, val} == 3'b1_0_1) begin
		$display ("Case 2 is passed");
		sol_cnt = sol_cnt + 1;
	end
	else begin
		$display ("Case 2 is failed");
	end

	{R, S, D} = 3'b1_0_0;
	#10
	$display("R = %b, S = %b, D = %b, Q = %b, Q' = %b, val = %b", R, S, D, Q, QN, val);
	#10
	if ({Q, QN, val} == 3'b0_1_1) begin
		$display ("Case 3 is passed");
		sol_cnt = sol_cnt + 1;
	end
	else begin
		$display ("Case 3 is failed");
	end

	{R, S, D} = 3'b1_0_1;
	#10
	$display("R = %b, S = %b, D = %b, Q = %b, Q' = %b, val = %b", R, S, D, Q, QN, val);
	#10
	if ({Q, QN, val} == 3'b0_1_1) begin
		$display ("Case 4 is passed");
		sol_cnt = sol_cnt + 1;
	end
	else begin
		$display ("Case 4 is failed");
	end

	{R, S, D} = 3'b0_1_0;
	#10
	$display("R = %b, S = %b, D = %b, Q = %b, Q' = %b, val = %b", R, S, D, Q, QN, val);
	#10
	if ({Q, QN, val} == 3'b1_0_1) begin
		$display ("Case 5 is passed");
		sol_cnt = sol_cnt + 1;
	end
	else begin
		$display ("Case 5 is failed");
	end

	{R, S, D} = 3'b0_1_1;
	#10
	$display("R = %b, S = %b, D = %b, Q = %b, Q' = %b, val = %b", R, S, D, Q, QN, val);
	#10
	if ({Q, QN, val} == 3'b1_0_1) begin
		$display ("Case 6 is passed");
		sol_cnt = sol_cnt + 1;
	end
	else begin
		$display ("Case 6 is failed");
	end

	{R, S, D} = 3'b1_1_0;
	#10
	$display("R = %b, S = %b, D = %b, Q = %b, Q' = %b, val = %b", R, S, D, Q, QN, val);
	#10
	if ({Q, QN, val} == 3'b1_1_0) begin
		$display ("Case 7 is passed");
		sol_cnt = sol_cnt + 1;
	end
	else begin
		$display ("Case 7 is failed");
	end

	{R, S, D} = 3'b1_1_1;
	#10
	$display("R = %b, S = %b, D = %b, Q = %b, Q' = %b, val = %b", R, S, D, Q, QN, val);
	#10
	if ({Q, QN, val} == 3'b1_1_0) begin
		$display ("Case 8 is passed");
		sol_cnt = sol_cnt + 1;
	end
	else begin
		$display ("Case 8 is failed");
	end

	$display ("Total score: %d", sol_cnt);
	$finish;
	end

	// Include the following lines to export waveform during simulation
	initial begin
				$dumpfile("tb_DFF_SR.vcd");
				$dumpvars();
		end
	///////////////////////////////////////////////

endmodule

Lab5_20160521_LeeJunhee/tb_DFF_SR.vcd
$date
	Sat Jun 05 15:58:21 2021
$end
$version
	Icarus Verilog
$end
$timescale
	1ps
$end
$scope module TEST_BENCH_DFF_SR $end
$var wire 1 ! Q $end
$var wire 1 " QN $end
$var wire 1 # val $end
$var reg 1 $ CLK $end
$var reg 1 % D $end
$var reg 1 & R $end
$var reg 1 ' S $end
$var reg 4 ( sol_cnt [3:0] $end
$scope module u_DFFSR $end
$var wire 1 ) CLK $end
$var wire 1 * D $end
$var wire 1 + R $end
$var wire 1 , S $end
$var wire 1 # val $end
$var reg 1 - Q $end
$var reg 1 . QN $end
$upscope $end
$upscope $end
$enddefinitions $end
#0
$dumpvars
x.
x-
0,
0+
0*
0)
b0 (
0'
0&
0%
0$
x#
x"
x!
$end
#6000
1#
0-
0!
1.
1"
1$
1)
#11000
0$
0)
#16000
1$
1)
#20000
1%
1*
b1 (
#21000
0$
0)
#26000
1-
1!
0.
0"
1$
1)
#31000
0$
0)
#36000
1$
1)
#40000
1&
1+
0%
0*
b10 (
#41000
0$
0)
#46000
0-
0!
1.
1"
1$
1)
#51000
0$
0)
#56000
1$
1)
#60000
1%
1*
b11 (
#61000
0$
0)
#66000
1$
1)
#71000
0$
0)
#76000
1$
1)
#80000
0&
0+
1'
1,
0%
0*
b100 (
#81000
0$
0)
#86000
1-
1!
0.
0"
1$
1)
#91000
0$
0)
#96000
1$
1)
#100000
1%
1*
b101 (
#101000
0$
0)
#106000
1$
1)
#111000
0$
0)
#116000
1$
1)
#120000
1&
1+
0%
0*
b110 (
#121000
0$
0)
#126000
0#
1.
1"
1$
1)
#131000
0$
0)
#136000
1$
1)
#140000
1%
1*
b111 (
#141000
0$
0)
#146000
1$
1)
#151000
0$
0)
#156000
1$
1)
#160000
b1000 (
