Lab3_20160521_LeeJunhee/fa1b.v
// 1-bit full adder module

module FULL_ADDER_1b(a, b, cin, s, cout);

	// a, b, and cin are inputs of 1-bit full adder
	input a;
	input b;
	input cin;

	// s and cout are outputs of 1-bit full adder
	output s;
	output cout;

///////////////////////////////////////
//
// write your code here
	assign s = a ^ b ^ cin;
	assign cout = (a & b) | (b & cin) | (a & cin);
//
///////////////////////////////////////

endmodule

Lab3_20160521_LeeJunhee/mul2b.v
// 2-bit Multiplier module
module MUL_2b(in1, in2, out);

	// in1 and in2 are 2-bit unsigned inputs of multiplier
	input [1:0] in1;
	input [1:0] in2;

	// out is 4-bit unsigned output of multiplier
	output [3:0] out;

///////////////////////////////////////
//
// write your code here
	reg [3:0] out_R;
	reg a1, b1, cin1, a2, b2, cin2;
	wire s1, cout1, s2, cout2;
	assign out = out_R;

	FULL_ADDER_1b FA1 (a1, b1, cin1, s1, cout1);
	FULL_ADDER_1b FA2 (a2, b2, cin2, s2, cout2);

	reg [2:0] in12;
	reg a3, b3, cin3, a4, b4, cin4, a5, b5, cin5;
	wire s3, cout3, s4, cout4, s5, cout5;
	FULL_ADDER_1b FA3 (a3, b3, cin3, s3, cout3);
	FULL_ADDER_1b FA4 (a4, b4, cin4, s4, cout4);
	FULL_ADDER_1b FA5 (a5, b5, cin5, s5, cout5);

	always @* begin
		if (in2 == 2'b00) begin
			out_R = 4'b0000;
		end
		else if (in2 == 2'b01) begin
			out_R = in1;
		end
		else if (in2 == 2'b10) begin
			a1 = in1[0];
			b1 = in1[0];
			cin1 = 1'b0;
			out_R[0] = s1;
			a2 = in1[1];
			b2 = in1[1];
			cin2 = cout1;
			out_R[1] = s2;
			out_R[2] = cout2;
		end
		else begin
			a1 = in1[0];
			b1 = in1[0];
			cin1 = 1'b0;
			in12[0] = s1;
			a2 = in1[1];
			b2 = in1[1];
			cin2 = cout1;
			in12[1] = s2;
			in12[2] = cout2;

			a3 = in1[0];
			b3 = in12[0];
			cin3 = 1'b0;
			out_R[0] = s3;
			a4 = in1[1];
			b4 = in12[1];
			cin4 = cout3;
			out_R[1] = s4;
			a5 = cout4;
			b5 = in12[2];
			cin5 = 1'b0;
			out_R[2] = s5;
			out_R[3] = cout5;
		end
	end
//
///////////////////////////////////////

endmodule

Lab3_20160521_LeeJunhee/tb_mul2b.v
// Testing workbench module for 2-bit multipier
`timescale 1ns/1ps	// Simulation precision

module TEST_BENCH_MUL2b;

	reg[1:0] in1;
	reg[1:0] in2;
	wire[3:0] out;
	reg  [3:0] sol_cnt;
	
	parameter SOLUTION_1 = 4'b0000;
	parameter SOLUTION_2 = 4'b0001;
	parameter SOLUTION_3 = 4'b0010;
	parameter SOLUTION_4 = 4'b0011;
	parameter SOLUTION_5 = 4'b0010;
	parameter SOLUTION_6 = 4'b0100;
	parameter SOLUTION_7 = 4'b0110;
	parameter SOLUTION_8 = 4'b0011;
	parameter SOLUTION_9 = 4'b0110;
	parameter SOLUTION_10 = 4'b1001;
	
	MUL_2b M_2b(in1, in2, out);
	
	initial begin

	sol_cnt = 0;
	in1=2'b00;
	in2=2'b00;
	#10 
	$display("in1 = %b, in2 = %b, out = %b",in1, in2, out);
	#10
	if (out==SOLUTION_1) begin
    $display ("Case 1 is passed");
    sol_cnt = sol_cnt + 1;
	end
	else begin
    $display ("Case 1 is failed");
	end
	
	in1=2'b01;
	in2=2'b01;
	#10 
	$display("in1 = %b, in2 = %b, out = %b",in1, in2, out);
	#10
	if (out==SOLUTION_2) begin
    $display ("Case 2 is passed");
    sol_cnt = sol_cnt + 1;
	end
	else begin
    $display ("Case 2 is failed");
	end
	
	in1=2'b01;
	in2=2'b10;
	#10 
	$display("in1 = %b, in2 = %b, out = %b",in1, in2, out);
	#10
	if (out==SOLUTION_3) begin
    $display ("Case 3 is passed");
    sol_cnt = sol_cnt + 1;
	end
	else begin
    $display ("Case 3 is failed");
	end
	
	in1=2'b01;
	in2=2'b11;
	#10 
	$display("in1 = %b, in2 = %b, out = %b",in1, in2, out);
	#10
	if (out==SOLUTION_4) begin
    $display ("Case 4 is passed");
    sol_cnt = sol_cnt + 1;
	end
	else begin
    $display ("Case 4 is failed");
	end
	
	in1=2'b10;
	in2=2'b01;
	#10 
	$display("in1 = %b, in2 = %b, out = %b",in1, in2, out);
	#10
	if (out==SOLUTION_5) begin
    $display ("Case 5 is passed");
    sol_cnt = sol_cnt + 1;
	end
	else begin
    $display ("Case 5 is failed");
	end
	
	in1=2'b10;
	in2=2'b10;
	#10 
	$display("in1 = %b, in2 = %b, out = %b",in1, in2, out);
	#10
	if (out==SOLUTION_6) begin
    $display ("Case 6 is passed");
    sol_cnt = sol_cnt + 1;
	end
	else begin
    $display ("Case 6 is failed");
	end
	
	in1=2'b10;
	in2=2'b11;
	#10 
	$display("in1 = %b, in2 = %b, out = %b",in1, in2, out);
	#10
	if (out==SOLUTION_7) begin
    $display ("Case 7 is passed");
    sol_cnt = sol_cnt + 1;
	end
	else begin
    $display ("Case 7 is failed");
	end
	
	in1=2'b11;
	in2=2'b01;
	#10 
	$display("in1 = %b, in2 = %b, out = %b",in1, in2, out);
	#10
	if (out==SOLUTION_8) begin
    $display ("Case 8 is passed");
    sol_cnt = sol_cnt + 1;
	end
	else begin
    $display ("Case 8 is failed");
	end
	
	in1=2'b11;
	in2=2'b10;
	#10 
	$display("in1 = %b, in2 = %b, out = %b",in1, in2, out);
	#10
	if (out==SOLUTION_9) begin
    $display ("Case 9 is passed");
    sol_cnt = sol_cnt + 1;
	end
	else begin
    $display ("Case 9 is failed");
	end
	
	in1=2'b11;
	in2=2'b11;
	#10 
	$display("in1 = %b, in2 = %b, out = %b",in1, in2, out);
	#10
	if (out==SOLUTION_10) begin
    $display ("Case 10 is passed");
    sol_cnt = sol_cnt + 1;
	end
	else begin
    $display ("Case 10 is failed");
	end
  
	
	$display ("Total score: %d", sol_cnt);
	end
	
	// Include the following lines to export waveform during simulation
	initial begin
        $dumpfile("tb_mul2b.vcd");
        $dumpvars();
    end
	
endmodule

Lab3_20160521_LeeJunhee/tb_mul2b.vcd
$date
	Wed May 26 16:39:18 2021
$end
$version
	Icarus Verilog
$end
$timescale
	1ps
$end
$scope module TEST_BENCH_MUL2b $end
$var wire 4 ! out [3:0] $end
$var reg 2 " in1 [1:0] $end
$var reg 2 # in2 [1:0] $end
$var reg 4 $ sol_cnt [3:0] $end
$scope module M_2b $end
$var wire 1 % cout1 $end
$var wire 1 & cout2 $end
$var wire 1 ' cout3 $end
$var wire 1 ( cout4 $end
$var wire 1 ) cout5 $end
$var wire 2 * in1 [1:0] $end
$var wire 2 + in2 [1:0] $end
$var wire 4 , out [3:0] $end
$var wire 1 - s1 $end
$var wire 1 . s2 $end
$var wire 1 / s3 $end
$var wire 1 0 s4 $end
$var wire 1 1 s5 $end
$var reg 1 2 a1 $end
$var reg 1 3 a2 $end
$var reg 1 4 a3 $end
$var reg 1 5 a4 $end
$var reg 1 6 a5 $end
$var reg 1 7 b1 $end
$var reg 1 8 b2 $end
$var reg 1 9 b3 $end
$var reg 1 : b4 $end
$var reg 1 ; b5 $end
$var reg 1 < cin1 $end
$var reg 1 = cin2 $end
$var reg 1 > cin3 $end
$var reg 1 ? cin4 $end
$var reg 1 @ cin5 $end
$var reg 3 A in12 [2:0] $end
$var reg 4 B out_R [3:0] $end
$scope module FA1 $end
$var wire 1 C a $end
$var wire 1 D b $end
$var wire 1 E cin $end
$var wire 1 % cout $end
$var wire 1 - s $end
$upscope $end
$scope module FA2 $end
$var wire 1 F a $end
$var wire 1 G b $end
$var wire 1 H cin $end
$var wire 1 & cout $end
$var wire 1 . s $end
$upscope $end
$scope module FA3 $end
$var wire 1 I a $end
$var wire 1 J b $end
$var wire 1 K cin $end
$var wire 1 ' cout $end
$var wire 1 / s $end
$upscope $end
$scope module FA4 $end
$var wire 1 L a $end
$var wire 1 M b $end
$var wire 1 N cin $end
$var wire 1 ( cout $end
$var wire 1 0 s $end
$upscope $end
$scope module FA5 $end
$var wire 1 O a $end
$var wire 1 P b $end
$var wire 1 Q cin $end
$var wire 1 ) cout $end
$var wire 1 1 s $end
$upscope $end
$upscope $end
$upscope $end
$enddefinitions $end
#0
$dumpvars
xQ
xP
xO
xN
xM
xL
xK
xJ
xI
xH
xG
xF
xE
xD
xC
b0 B
bx A
x@
x?
x>
x=
x<
x;
x:
x9
x8
x7
x6
x5
x4
x3
x2
x1
x0
x/
x.
x-
b0 ,
b0 +
b0 *
x)
x(
x'
x&
x%
b0 $
b0 #
b0 "
b0 !
$end
#20000
b1 B
b1 !
b1 ,
b1 #
b1 +
b1 "
b1 *
b1 $
#40000
1.
1=
1H
0&
1%
0-
08
0G
03
0F
b10 B
b10 !
b10 ,
0<
0E
17
1D
12
1C
b10 #
b10 +
b10 $
#60000
01
06
0O
0(
10
0?
0N
0'
0)
1/
0@
0Q
0;
0P
1:
1M
05
0L
b11 B
b11 !
b11 ,
0>
0K
09
0J
14
1I
b10 A
b11 #
b11 +
b11 $
#80000
b10 B
b10 !
b10 ,
b1 #
b1 +
b10 "
b10 *
b100 $
#100000
0.
b100 !
b100 ,
0=
0H
0%
1&
18
1G
13
1F
b100 B
07
0D
02
0C
b10 #
b10 +
b101 $
#120000
11
0/
1;
1P
0:
0M
15
1L
b110 B
b110 !
b110 ,
04
0I
b100 A
b11 #
b11 +
b110 $
#140000
b11 B
b11 !
b11 ,
b1 #
b1 +
b11 "
b11 *
b111 $
#160000
1.
1=
1H
1%
b110 B
b110 !
b110 ,
17
1D
12
1C
b10 #
b10 +
b1000 $
#180000
1)
01
16
1O
1(
b1001 !
b1001 ,
00
1/
1:
1M
b1001 B
14
1I
b110 A
b11 #
b11 +
b1001 $
#200000
b1010 $
